tfprotocol_client/__init__.py
tfprotocol_client/connection/__init__.py
tfprotocol_client/connection/client.py
tfprotocol_client/connection/codes_sender_recvr.py
tfprotocol_client/connection/keep_alive_thread.py
tfprotocol_client/connection/protocol_client.py
tfprotocol_client/connection/socks_prox.py
tfprotocol_client/extensions/__init__.py
tfprotocol_client/extensions/xs_mysql.py
tfprotocol_client/extensions/xs_postgresql.py
tfprotocol_client/extensions/xs_sql_super.py
tfprotocol_client/extensions/xs_sqlite.py
tfprotocol_client/misc/__init__.py
tfprotocol_client/misc/build_utils.py
tfprotocol_client/misc/constants.py
tfprotocol_client/misc/handlers_aliases.py
tfprotocol_client/misc/parse_utils.py
tfprotocol_client/misc/thread.py
tfprotocol_client/misc/timeout_func.py
tfprotocol_client/models/__init__.py
tfprotocol_client/models/exceptions.py
tfprotocol_client/models/file_stat.py
tfprotocol_client/models/keepalive_options.py
tfprotocol_client/models/message.py
tfprotocol_client/models/proxy_options.py
tfprotocol_client/models/putget_commands.py
tfprotocol_client/models/status_info.py
tfprotocol_client/models/status_server_code.py
tfprotocol_client/models/tcptimeout_options.py
tfprotocol_client/models/transfer_state.py
tfprotocol_client/security/cryptography.py
tfprotocol_client/security/hash_utils.py
tfprotocol_client/tfprotocol.py
tfprotocol_client/tfprotocol_keepalive.py
tfprotocol_client/tfprotocol_super.py
tfprotocol_client-1.2.2.dist-info/LICENSE.rst
tfprotocol_client-1.2.2.dist-info/WHEEL
tfprotocol_client-1.2.2.dist-info/METADATA
tfprotocol_client-1.2.2.dist-info/RECORD
