Metadata-Version: 2.1
Name: tfprotocol-client
Version: 1.2.2
Summary: Transfer Protocol client implemented in python.
Home-page: https://github.com/lagcleaner/tfprotocol_client_py
License: LICENSE.rst
Keywords: transfer,protocol,client,python,tfproto,tfprotocol
Author: Leonel Garcia
Author-email: lagcleaner@gmail.com
Requires-Python: >=3.7.2,<4.0.0
Classifier: Development Status :: 5 - Production/Stable
Classifier: Environment :: Console
Classifier: Intended Audience :: Developers
Classifier: Intended Audience :: System Administrators
Classifier: License :: Other/Proprietary License
Classifier: Operating System :: OS Independent
Classifier: Programming Language :: Python :: 3
Classifier: Programming Language :: Python :: 3.8
Classifier: Programming Language :: Python :: 3.9
Classifier: Programming Language :: Python :: 3.10
Classifier: Programming Language :: Python :: 3.11
Classifier: Topic :: Communications :: File Sharing
Requires-Dist: multipledispatch (>=0.6.0,<0.7.0)
Requires-Dist: pycryptodome (>=3.15.0,<4.0.0)
Project-URL: Repository, https://github.com/lagcleaner/tfprotocol_client_py
